jonze/BahdanauAttention.py
jonze/BaselineModel.py
jonze/CustomBahdanauAttention.py
jonze/CustomDropout.py
jonze/SlotGate.py
jonze/SlotGatedModel.py
jonze/__init__.py
jonze/__main__.py
jonze/utils.py
src/BahdanauAttention.py
src/BaselineModel.py
src/CustomBahdanauAttention.py
src/CustomDropout.py
src/SlotGate.py
src/SlotGatedModel.py
src/__init__.py
src/main.py
src/utils.py
jonze-0.0.20.dist-info/LICENSE
jonze-0.0.20.dist-info/METADATA
jonze-0.0.20.dist-info/WHEEL
jonze-0.0.20.dist-info/top_level.txt
jonze-0.0.20.dist-info/RECORD
