Metadata-Version: 2.1
Name: jonze
Version: 0.0.20
Summary: Reusable Joint Slot and Intent Extraction implementation in Tensorflow2.0
Home-page: https://github.com/zeionara/jonze
Author: Zeio Nara
Author-email: zeionara@gmail.com
License: UNKNOWN
Platform: UNKNOWN
Classifier: Programming Language :: Python :: 3
Classifier: License :: OSI Approved :: MIT License
Classifier: Operating System :: OS Independent
Requires-Python: >=3.6
